{"cameraMode":{"drawMode":0,"name":"Shaded","section":"Shading Mode"},"sceneLighting":true,"audioPlay":false,"sceneViewState":{"m_AlwaysRefresh":false,"showFog":true,"showSkybox":true,"showFlares":true,"showImageEffects":true,"showParticleSystems":true,"showVisualEffectGraphs":true,"m_FxEnabled":true},"in2DMode":false,"pivot":{"x":9.74634075164795,"y":5.531139373779297,"z":-7.201272487640381},"rotation":{"x":0.021926365792751313,"y":-0.638117790222168,"z":0.01820000819861889,"w":0.7694005966186523},"size":5.147041320800781,"orthographic":false}